[{"brandName":"Milky Mist","productName":"Milky Mist Paneer","quantity":"200 g","price":"₹75","MRP":"₹92","imageUrl":"https://github.com/Shiivani/product-db/blob/master/milky-mist-panner.jpg?raw=true","offerText":"18% OFF"},{"brandName":"Aashirvaad","productName":"Aashirvaad Shudh Chakki Whole Wheat Atta","quantity":"10 kg","price":"₹375","MRP":"₹465","imageUrl":"https://github.com/Shiivani/product-db/blob/master/aashirvaad-shudh-chakki-atta.jpg?raw=true","offerText":"19% OFF"},{"brandName":"Maggi","productName":"Maggi Masala Noodles","quantity":"560 g (Pack of 8)","price":"₹75","MRP":"₹89","imageUrl":"https://github.com/Shiivani/product-db/blob/master/maggi-masala.jpg?raw=true","offerText":"15% OFF"},{"brandName":"Himalaya","productName":"Himalaya Gentle Baby Shampoo","quantity":"400 ml","price":"₹165","MRP":"₹275","imageUrl":"https://github.com/Shiivani/product-db/blob/master/himalaya-baby-shampoo.jpg?raw=true","offerText":"40% OFF"},{"brandName":"Parachute","productName":"Parachute Pure Coconut Oil (Plastic Bottle)","quantity":"600 ml","price":"₹189","MRP":"₹250","imageUrl":"https://github.com/Shiivani/product-db/blob/master/milky-mist-panner.jpg?raw=true","offerText":"24% OFF"},{"brandName":"Amul","productName":"Amul Pure Ghee","quantity":"1 L Carton","price":"₹469","MRP":"₹480","imageUrl":"https://github.com/Shiivani/product-db/blob/master/amul-pure-ghee.jpg?raw=true","offerText":"3% OFF"},{"brandName":"Surf Excel","productName":"Surf Excel Matic Front Load Detergent Powder (Carton)","quantity":"2 kg","price":"₹376","MRP":"₹530","imageUrl":"https://github.com/Shiivani/product-db/blob/master/surf-excel.jpg?raw=true","offerText":"29% OFF"},{"brandName":"Patanjali","productName":"Patanjali Cow Ghee","quantity":"1 L Carton","price":"₹495","MRP":"₹550","imageUrl":"https://github.com/Shiivani/product-db/blob/master/patanjali-cow-ghee.jpg?raw=true","offerText":"10% OFF"},{"brandName":"Grofers Mother's","productName":"Grofers Mother's Choice Desi Ghee","quantity":"1 l","price":"₹414","MRP":"₹450","imageUrl":"https://github.com/Shiivani/product-db/blob/master/grofers-desi-ghee.jpg?raw=true","offerText":"8% OFF"},{"brandName":"Milkfood","productName":"Milkfood Rich Desi Danedar Ghee(Carton)","quantity":"1l","price":"₹408","MRP":"₹498","imageUrl":"https://github.com/Shiivani/product-db/blob/master/milkfood-rich-desi-ghee.jpg?raw=true","offerText":"18% OFF"}]